[
null,
{"id":1,"expanded":true,"name":"WorldMap","order":1,"parentId":0,"scrollX":6494.4,"scrollY":3682.2},
{"id":2,"expanded":true,"name":"BACKUP","order":2,"parentId":0,"scrollX":723.6,"scrollY":469.79999999999995},
{"id":3,"expanded":true,"name":"WorldMap","order":3,"parentId":2,"scrollX":6312,"scrollY":3682.2},
{"id":4,"expanded":true,"name":"Arcanica","order":4,"parentId":0,"scrollX":714,"scrollY":460.2},
{"id":5,"expanded":true,"name":"Home","order":5,"parentId":4,"scrollX":723.6,"scrollY":469.79999999999995},
{"id":6,"expanded":false,"name":"OutsideHouse","order":6,"parentId":4,"scrollX":714,"scrollY":490.2},
{"id":7,"expanded":true,"name":"Village1","order":7,"parentId":4,"scrollX":714,"scrollY":460.2},
{"id":8,"expanded":true,"name":"MAP008","order":11,"parentId":4,"scrollX":723.6,"scrollY":469.79999999999995},
{"id":9,"expanded":false,"name":"Normal Town","order":12,"parentId":8,"scrollX":714,"scrollY":460.2},
{"id":10,"expanded":false,"name":"Market","order":13,"parentId":8,"scrollX":714,"scrollY":730.1999999999999},
{"id":11,"expanded":true,"name":"House1","order":8,"parentId":7,"scrollX":723.6,"scrollY":469.79999999999995},
{"id":12,"expanded":false,"name":"House2","order":9,"parentId":7,"scrollX":723.6,"scrollY":469.79999999999995},
{"id":13,"expanded":true,"name":"StorageShed","order":10,"parentId":7,"scrollX":723.6,"scrollY":469.79999999999995},
{"id":14,"expanded":false,"name":"Intro","order":14,"parentId":0,"scrollX":723.6,"scrollY":469.79999999999995}
]